drf_writable_nested_fullclean/__init__.py
drf_writable_nested_fullclean/mixins.py
drf_writable_nested_fullclean/serializers.py
drf_writable_nested_fullclean/utils.py
drf_writable_nested_fullclean-0.0.1.dist-info/LICENSE
drf_writable_nested_fullclean-0.0.1.dist-info/METADATA
drf_writable_nested_fullclean-0.0.1.dist-info/WHEEL
drf_writable_nested_fullclean-0.0.1.dist-info/top_level.txt
drf_writable_nested_fullclean-0.0.1.dist-info/RECORD
