Metadata-Version: 2.1
Name: drf-writable-nested-fullclean
Version: 0.0.1
Summary: Call django model full_clean() when validate WritableNestedModelSerializer
Home-page: https://github.com/giuseppenovielli/drf-writable-nested-fullclean
Author: Giuseppe Novielli
Author-email: novielligiuseppe@gmail.com
License: MIT License
Project-URL: Documentation, https://github.com/giuseppenovielli/drf-writable-nested-fullclean?tab=readme-ov-file#drf-writable-nested-fullclean
Project-URL: Funding, https://buymeacoffee.com/giuseppedev
Project-URL: Source, https://github.com/giuseppenovielli/drf-writable-nested-fullclean
Project-URL: Tracker, https://github.com/giuseppenovielli/drf-writable-nested-fullclean/issues
Keywords: django-rest-framework,model-serializer,validate,full_clean,writable-nested,writable-nested-serializer,writable-nested-fullclean,writable-nested-fullclean-serializer
Classifier: Programming Language :: Python :: 3
Classifier: License :: OSI Approved :: MIT License
Classifier: Operating System :: OS Independent
Classifier: Environment :: Web Environment
Classifier: Framework :: Django
Classifier: Intended Audience :: Developers
Classifier: Operating System :: OS Independent
Classifier: Development Status :: 1 - Planning
Requires-Python: >=3.7
License-File: LICENSE
Requires-Dist: djangorestframework>=3.0.0
Requires-Dist: drf-writable-nested==0.7.0
Requires-Dist: drf-fullclean
